snek_paginator/__init__.py
snek_paginator/paginator.py
snek_paginator-1.0.0.dist-info/LICENSE
snek_paginator-1.0.0.dist-info/METADATA
snek_paginator-1.0.0.dist-info/WHEEL
snek_paginator-1.0.0.dist-info/top_level.txt
snek_paginator-1.0.0.dist-info/RECORD
