Metadata-Version: 2.1
Name: snek-paginator
Version: 1.0.0
Summary: Paginator for Dis-Snek Python Discord API wrapper
Home-page: https://github.com/Toricane/snek-paginator
Author: Toricane
Author-email: prjwl028@gmail.com
License: GNU
Platform: UNKNOWN
Classifier: Programming Language :: Python :: 3
Classifier: Development Status :: 4 - Beta
Classifier: License :: OSI Approved :: GNU General Public License v3 (GPLv3)
Classifier: Operating System :: OS Independent
License-File: LICENSE
Requires-Dist: dis-snek
